{"a": "b", "10": {"Lawrence Page": [["http://dbpedia.org/resource/Larry_Page", "Lawrence Page", 1.0]], "Michigan": [["http://dbpedia.org/resource/Michigan", "Michigan", 0.15891731339466397]], "East Lansing": [["http://dbpedia.org/resource/East_Lansing,_Michigan", "East Lansing", 0.9675112225315373]], "Larry Page": [["http://dbpedia.org/resource/Larry_Page", "Larry Page", 0.9823092142725424]]}, "13": {"Compaq Computers": [["http://dbpedia.org/resource/", "Compaq Computers", 0]], "Elon Musk": [["http://dbpedia.org/resource/Elon_Musk", "Elon Musk", 1.0]], "South Africa": [["http://dbpedia.org/resource/South_Africa", "South Africa", 0.5937579037234549]]}, "12": {"Gloria Page": [["http://dbpedia.org/resource/", "Gloria Page", 0]], "Larry Page": [["http://dbpedia.org/resource/Larry_Page", "Larry Page", 1.0]]}, "15": {"Facebook": [["http://dbpedia.org/resource/Facebook", "Facebook", 0.9596902470874105]], "Sheryl Sandberg": [["http://dbpedia.org/resource/Sheryl_Sandberg", "Sheryl Sandberg", 1.0]]}, "14": {"SpaceX": [["http://dbpedia.org/resource/SpaceX", "SpaceX", 1.0]], "Elon Musk": [["http://dbpedia.org/resource/Elon_Musk", "Elon Musk", 1.0]], "Tesla Motors": [["http://dbpedia.org/resource/Tesla_Motors", "Tesla Motors", 1.0]]}, "16": {"Sandberg": [["http://dbpedia.org/resource/Sheryl_Sandberg", "Sandberg", 0.2238728673913066]], "Google": [["http://dbpedia.org/resource/Google", "Google", 0.895817131580393]], "Silicon Valley": [["http://dbpedia.org/resource/Silicon_Valley", "Silicon Valley", 0.9405808377190925]]}, "11": {"Carl Page": [["http://dbpedia.org/resource/", "Carl Page", 0]]}, "1": {"Franklin D. Roosevelt": [["http://dbpedia.org/resource/Franklin_D._Roosevelt", "Franklin D. Roosevelt", 0.9397327145591381]], "Hyde Park": [["http://dbpedia.org/resource/Hyde_Park,_New_York", "Hyde Park", 0.14840121933616354]], "New York": [["http://dbpedia.org/resource/", "New York", 0]]}, "3": {"Georgia": [["http://dbpedia.org/resource/Georgia_%28U.S._state%29", "Georgia", 0.1008653601791589]], "Roosevelt": [["http://dbpedia.org/resource/Franklin_D._Roosevelt", "Roosevelt", 0.16026388276866477]]}, "2": {"U.S.": [["http://dbpedia.org/resource/United_States", "U.S.", 0.7982840204926069]], "Franklin D. Roosevelt": [["http://dbpedia.org/resource/Franklin_D._Roosevelt", "Franklin D. Roosevelt", 0.9414625383760842]]}, "5": {"Treasury": [["http://dbpedia.org/resource/United_States_Department_of_the_Treasury", "Treasury", 0.2746362999189833]], "Federal Reserve": [["http://dbpedia.org/resource/Federal_Reserve_System", "Federal Reserve", 0.930426903606521]], "Rockefeller": [["http://dbpedia.org/resource/David_Rockefeller", "Rockefeller", 0.08427790649167738]], "Eisenhower": [["http://dbpedia.org/resource/Dwight_D._Eisenhower", "Eisenhower", 0.8428795663314359]]}, "4": {"David Rockefeller": [["http://dbpedia.org/resource/David_Rockefeller", "David Rockefeller", 0.9896051497459548]], "America": [["http://dbpedia.org/resource/United_States", "America", 0.21381209275652402]], "John D. Rockefeller": [["http://dbpedia.org/resource/John_D._Rockefeller", "John D. Rockefeller", 1.0]]}, "7": {"Scranton": [["http://dbpedia.org/resource/Scranton,_Pennsylvania", "Scranton", 0.13579813785660366]], "U.S.": [["http://dbpedia.org/resource/United_States", "U.S.", 0.7006313240731253]], "Joe Biden": [["http://dbpedia.org/resource/Joe_Biden", "Joe Biden", 1.0]], "United States": [["http://dbpedia.org/resource/United_States", "United States", 0.16724154038525968]], "Pennsylvania": [["http://dbpedia.org/resource/Pennsylvania", "Pennsylvania", 0.7402221676940847]], "Barack Obama": [["http://dbpedia.org/resource/Barack_Obama", "Barack Obama", 0.9601987022346514]], "Joseph Robinette Biden": [["http://dbpedia.org/resource/Joe_Biden", "Joseph Robinette Biden", 1.0]]}, "6": {"Chase Manhattan Bank": [["http://dbpedia.org/resource/Chase_Bank", "Chase Manhattan Bank", 0.9565993196583112]], "Rockefeller": [["http://dbpedia.org/resource/Nelson_Rockefeller", "Rockefeller", 0.13776180179236025]]}, "9": {"Biden": [["http://dbpedia.org/resource/Joe_Biden", "Biden", 1.0]], "Neilia Hunter": [["http://dbpedia.org/resource/", "Neilia Hunter", 0]]}, "8": {"Pennsylvania": [["http://dbpedia.org/resource/Pennsylvania", "Pennsylvania", 0.7083623426296136]], "Syracuse University": [["http://dbpedia.org/resource/Syracuse_University", "Syracuse University", 0.9061132142915459]], "Scranton": [["http://dbpedia.org/resource/Scranton,_Pennsylvania", "Scranton", 0.19914629526970962]], "Delaware": [["http://dbpedia.org/resource/", "Delaware", 0]], "Biden": [["http://dbpedia.org/resource/Joe_Biden", "Biden", 0.9490614401836899]], "New York": [["http://dbpedia.org/resource/", "New York", 0]], "University of Delaware": [["http://dbpedia.org/resource/University_of_Delaware", "University of Delaware", 0.9652840616698755]], "New Castle county": [["http://dbpedia.org/resource/New_Castle_County,_Delaware", "New Castle county", 1.0]]}}