{"Ca2": "California", "Ti": "Tim_Cook", "Lu": "Luca_Maestri", "St3": "Steve_Wozniak", "Ro": "Ronald_Wayne", "Be": "Beats_Electronics", "Wa": "Washington_(state)", "Bi": "Bill_Gates", "Jo": "Jonathan_Ive", "Br": "Braeburn_Capital", "Je": "Jeff_Williams_(Apple)", "Mi": "Microsoft", "St": "Steve_Jobs", "Un": "United_States", "Fi": "FileMaker_Inc.", "Se": "Seattle", "Ca": "Cascade_Investment", "An": "Anobit", "Ap": "Apple_Inc.", "Ar": "Arthur_D._Levinson", "Cu": "Cupertino,_California", "Bi1": "Bill_&_Melinda_Gates_Foundation"}